createPackageTurner/__init__.py
createPackageTurner/createPackageTurner.py
createPackageTurner-0.2.49.dist-info/METADATA
createPackageTurner-0.2.49.dist-info/WHEEL
createPackageTurner-0.2.49.dist-info/top_level.txt
createPackageTurner-0.2.49.dist-info/RECORD
