Metadata-Version: 2.2
Name: createPackageTurner
Version: 0.2.49
Summary: **createPackageTurner** is an automated Python package creation tool designed to quickly turn a Python class into a fully functional Python package. It generates the required package structure, metadata, setup files, and optionally publishes the package to PyPI. By providing an input class or function, you can automatically generate a Python package and optionally upload it to PyPI for distribution.
Home-page: https://github.com/brighamturner12/packageMakerTurner.git
Author: Brigham Turner
Author-email: brighamturner@narratebay.com
License: MIT
Project-URL: Documentation, https://github.com/brighamturner12/packageMakerTurner/blob/main/readme.md
Project-URL: Source Code, https://github.com/brighamturner12/packageMakerTurner/blob/main/packageMaker_source.py
Classifier: Programming Language :: Python :: 3
Classifier: License :: OSI Approved :: MIT License
Classifier: Operating System :: OS Independent
Requires-Python: >=3.6
Requires-Dist: pip
Requires-Dist: twine
Dynamic: author
Dynamic: author-email
Dynamic: classifier
Dynamic: description
Dynamic: description-content-type
Dynamic: home-page
Dynamic: license
Dynamic: project-url
Dynamic: requires-dist
Dynamic: requires-python
Dynamic: summary
